README.md
setup.py
cone_search_plus/__init__.py
cone_search_plus/csp.py
cone_search_plus/setup_package.py
cone_search_plus.egg-info/PKG-INFO
cone_search_plus.egg-info/SOURCES.txt
cone_search_plus.egg-info/dependency_links.txt
cone_search_plus.egg-info/requires.txt
cone_search_plus.egg-info/top_level.txt