Metadata-Version: 1.1
Name: cone-search-plus
Version: 0.2.0
Summary: Search the sky for targets using a variety of tunable constraints
Home-page: https://github.com/hover2pi/cone_search_plus
Author: Joe Filippazzo, Neil Zimmerman
Author-email: jfilippazzo@stsci.edu
License: MIT
Keywords: astrophysics
Platform: UNKNOWN
Classifier: Development Status :: 4 - Beta
Classifier: Intended Audience :: Science/Research
Classifier: License :: OSI Approved :: MIT License
Classifier: Programming Language :: Python
